setup.py
calc_distributions/Binomialdistribution.py
calc_distributions/Gaussiandistribution.py
calc_distributions/Generaldistribution.py
calc_distributions/__init__.py
calc_distributions.egg-info/PKG-INFO
calc_distributions.egg-info/SOURCES.txt
calc_distributions.egg-info/dependency_links.txt
calc_distributions.egg-info/not-zip-safe
calc_distributions.egg-info/top_level.txt