Metadata-Version: 1.0
Name: calc-distributions
Version: 0.1
Summary: Gaussian distributions
Home-page: UNKNOWN
Author: Sadeko Daniel
Author-email: sadekodaniel@gmail.com
License: UNKNOWN
Platform: UNKNOWN
